client/__init__.py
client/__main__.py
client/client.py
kollin_content_client/__init__.py
kollin_content_client/__main__.py
kollin_content_client/client.py
kollin_content-1.0.0.dist-info/METADATA
kollin_content-1.0.0.dist-info/WHEEL
kollin_content-1.0.0.dist-info/top_level.txt
kollin_content-1.0.0.dist-info/RECORD
