Metadata-Version: 2.1
Name: kollin-content
Version: 1.0.0
Summary: Packages related to automatic content management at kollin
Home-page: https://github.com/crash-course-sverige/content-client
Author: Nicolas Jonason
Author-email: nicolasjonason@gmail.com
License: MIT
Platform: UNKNOWN
Classifier: License :: OSI Approved :: MIT License
Classifier: Programming Language :: Python :: 3
Classifier: Programming Language :: Python :: 3.7
